fa/__init__.py
fa/_version.py
fa/context.py
fa/fa_types.py
fa/fainterp.py
fa/ida_launcher.py
fa/ida_plugin.py
fa/utils.py
fa/commands/__init__.py
fa/commands/add.py
fa/commands/add_offset_range.py
fa/commands/alias
fa/commands/align.py
fa/commands/argument.py
fa/commands/b.py
fa/commands/clear.py
fa/commands/deref_data.py
fa/commands/find.py
fa/commands/find_bytes.py
fa/commands/find_bytes_ida.py
fa/commands/find_immediate.py
fa/commands/find_str.py
fa/commands/function_end.py
fa/commands/function_lines.py
fa/commands/function_start.py
fa/commands/goto_ref.py
fa/commands/if.py
fa/commands/if_not.py
fa/commands/intersect.py
fa/commands/keystone_find_opcodes.py
fa/commands/keystone_verify_opcodes.py
fa/commands/load.py
fa/commands/locate.py
fa/commands/make_code.py
fa/commands/make_comment.py
fa/commands/make_function.py
fa/commands/make_literal.py
fa/commands/make_offset.py
fa/commands/make_unknown.py
fa/commands/max_xrefs.py
fa/commands/min_xrefs.py
fa/commands/most_common.py
fa/commands/next_instruction.py
fa/commands/offset.py
fa/commands/operand.py
fa/commands/print.py
fa/commands/python_if.py
fa/commands/run.py
fa/commands/set_const.py
fa/commands/set_enum.py
fa/commands/set_name.py
fa/commands/set_struct_member.py
fa/commands/set_type.py
fa/commands/single.py
fa/commands/sort.py
fa/commands/stop_if_empty.py
fa/commands/store.py
fa/commands/symdiff.py
fa/commands/trace.py
fa/commands/union.py
fa/commands/unique.py
fa/commands/verify_aligned.py
fa/commands/verify_bytes.py
fa/commands/verify_name.py
fa/commands/verify_opcode.py
fa/commands/verify_operand.py
fa/commands/verify_ref.py
fa/commands/verify_segment.py
fa/commands/verify_single.py
fa/commands/verify_str.py
fa/commands/xref.py
fa/commands/xrefs_to.py
fa/res/icons/create_sig.png
fa/res/icons/export.png
fa/res/icons/find.png
fa/res/icons/find_all.png
fa/res/icons/save.png
fa/res/icons/settings.png
fa/res/icons/suitcase.png
fa/res/screenshots/menu.png
fa/signatures/test-project-elf/alias
fa-1.0.9.dist-info/LICENSE
fa-1.0.9.dist-info/METADATA
fa-1.0.9.dist-info/WHEEL
fa-1.0.9.dist-info/top_level.txt
fa-1.0.9.dist-info/RECORD
