Metadata-Version: 2.2
Name: fa
Version: 1.0.9
Summary: Automation tool for locating symbols & structs in binary (primarily IDA focused)
Author-email: doronz88 <doron88@gmail.com>
Maintainer-email: doronz88 <doron88@gmail.com>
License: GNU GENERAL PUBLIC LICENSE Version 3, 29 June 2007
Project-URL: Homepage, https://github.com/doronz88/fa
Project-URL: Bug Reports, https://github.com/doronz88/fa/issues
Keywords: reverse-engineering,ida,automation,signatures,symbols
Classifier: Development Status :: 5 - Production/Stable
Classifier: License :: OSI Approved :: GNU General Public License v3 or later (GPLv3+)
Classifier: Programming Language :: Python :: 3
Classifier: Programming Language :: Python :: 3.8
Classifier: Programming Language :: Python :: 3.9
Classifier: Programming Language :: Python :: 3.10
Classifier: Programming Language :: Python :: 3.11
Classifier: Programming Language :: Python :: 3.12
Classifier: Programming Language :: Python :: 3 :: Only
Requires-Python: >=3.8
License-File: LICENSE
Requires-Dist: keystone-engine
Requires-Dist: capstone
Requires-Dist: click
Requires-Dist: hjson
Requires-Dist: future
Requires-Dist: configparser
Requires-Dist: six
Requires-Dist: rpyc
Requires-Dist: click
Requires-Dist: ipython
Requires-Dist: termcolor
Provides-Extra: test
Requires-Dist: pytest; extra == "test"
